setup.py
HelloBikeLibrary2/__init__.py
HelloBikeLibrary2/common.py
HelloBikeLibrary2/data_conversion.py
HelloBikeLibrary2/request.py
HelloBikeLibrary2/version.py
HelloBikeLibrary2.egg-info/PKG-INFO
HelloBikeLibrary2.egg-info/SOURCES.txt
HelloBikeLibrary2.egg-info/dependency_links.txt
HelloBikeLibrary2.egg-info/top_level.txt