Metadata-Version: 1.2
Name: HelloBikeLibrary2
Version: 1.0.0
Summary: test framework
Home-page: UNKNOWN
Author: maoyongfan
Author-email: maoyongfan@163.com
License: MIT
Keywords: api test python language frameworks
Platform: UNKNOWN
Classifier: Development Status :: 3 - Alpha
Classifier: Intended Audience :: Developers
Classifier: Topic :: Software Development :: Build Tools
Classifier: License :: OSI Approved :: MIT License
Classifier: Programming Language :: Python :: 3
Classifier: Programming Language :: Python :: 3.6
Classifier: Operating System :: OS Independent
Requires-Python: >=3
